a2squery/__init__.py
a2squery/data.py
a2squery/enums.py
a2squery/exceptions.py
a2squery/parser.py
a2squery/query.py
a2squery-0.0.2.dist-info/LICENSE.txt
a2squery-0.0.2.dist-info/METADATA
a2squery-0.0.2.dist-info/WHEEL
a2squery-0.0.2.dist-info/top_level.txt
a2squery-0.0.2.dist-info/RECORD
