Metadata-Version: 2.1
Name: a2squery
Version: 0.0.2
Summary: A2SQuery is a python implementation of Valve's A2S protocol
Home-page: https://github.com/linKhehe/a2squery
Author: linKhehe
License: MIT
Project-URL: Documentation, https://a2squery.readthedocs.io/en/latest/
Project-URL: Issue tracker, https://github.com/linKhehe/a2squery/issues
Classifier: License :: OSI Approved :: MIT License
Classifier: Intended Audience :: Developers
Classifier: Natural Language :: English
Classifier: Operating System :: OS Independent
Classifier: Programming Language :: Python :: 3.6
Classifier: Programming Language :: Python :: 3.7
Classifier: Programming Language :: Python :: 3.8
Classifier: Programming Language :: Python :: 3.9
Classifier: Programming Language :: Python :: 3.10
Requires-Python: >=3.6.0
License-File: LICENSE.txt
Provides-Extra: docs
